README.rst
setup.py
src/PyBiomech/__init__.py
src/PyBiomech/btkio.py
src/PyBiomech/contacts.py
src/PyBiomech/fio.py
src/PyBiomech/geom.py
src/PyBiomech/kine.py
src/PyBiomech/kine_fr.py
src/PyBiomech/kine_or.py
src/PyBiomech/kine_sr.py
src/PyBiomech/kine_wr.py
src/PyBiomech/ligaments.py
src/PyBiomech/mplh.py
src/PyBiomech/procedure_or.py
src/PyBiomech/procedure_rig.py
src/PyBiomech/procedure_spine.py
src/PyBiomech/procedure_sr.py
src/PyBiomech/pyver.py
src/PyBiomech/rotations.py
src/PyBiomech/spine.py
src/PyBiomech/utils.py
src/PyBiomech/viconio.py
src/PyBiomech/vtkh.py
src/PyBiomech.egg-info/PKG-INFO
src/PyBiomech.egg-info/SOURCES.txt
src/PyBiomech.egg-info/dependency_links.txt
src/PyBiomech.egg-info/requires.txt
src/PyBiomech.egg-info/top_level.txt