Metadata-Version: 1.0
Name: PyBiomech
Version: 1.9.0
Summary: Collection of tools for certain biomechanical pipelines
Home-page: https://github.com/u0078867/PyBiomech
Author: u0078867
Author-email: davide.monari@kuleuven.be
License: MIT
Platform: UNKNOWN
